[
  {
    "id": "owner-001",
    "name": "Norman Sanchez",
    "team": "Android Team",
    "email": "norman.sanchez@shell.com",
    "documentIDs": ["doc-001", "doc-002"]
  },
  {
    "id": "owner-002",
    "name": "Sara Kim",
    "team": "Mobile Platform Team",
    "email": "sara.kim@shell.com",
    "documentIDs": ["doc-004", "doc-005"]
  },
  {
    "id": "owner-003",
    "name": "Alex Rodriguez",
    "team": "Platform Team",
    "email": "alex.rodriguez@shell.com",
    "documentIDs": ["doc-003"]
  },
  {
    "id": "owner-004",
    "name": "Carlos Mendez",
    "team": "DevOps Team",
    "email": "carlos.mendez@shell.com",
    "documentIDs": ["doc-006"]
  }
]
